README.rst
setup.py
acrawler/__init__.py
acrawler/chain.py
acrawler/counter.py
acrawler/crawler.py
acrawler/exceptions.py
acrawler/handlers.py
acrawler/http.py
acrawler/item.py
acrawler/middleware.py
acrawler/parser.py
acrawler/processors.py
acrawler/scheduler.py
acrawler/setting.py
acrawler/task.py
acrawler/utils.py
acrawler/web.py
acrawler.egg-info/PKG-INFO
acrawler.egg-info/SOURCES.txt
acrawler.egg-info/dependency_links.txt
acrawler.egg-info/requires.txt
acrawler.egg-info/top_level.txt