Metadata-Version: 1.2
Name: acrawler
Version: 0.1.5
Summary: A simple web-crawling framework, based on aiohttp.
Home-page: https://github.com/wooddance/aCrawler
Author: wooddance
Author-email: zireael.me@gmail.com
License: UNKNOWN
Platform: UNKNOWN
Requires-Python: >=3.6.0
